xtreamcodeserver/__init__.py
xtreamcodeserver/__main__.py
xtreamcodeserver/httprequesthandler.py
xtreamcodeserver/server.py
xtreamcodeserver/credentials/credentials.py
xtreamcodeserver/entry/category.py
xtreamcodeserver/entry/container.py
xtreamcodeserver/entry/entry.py
xtreamcodeserver/entry/live.py
xtreamcodeserver/entry/serie.py
xtreamcodeserver/entry/serie_episode.py
xtreamcodeserver/entry/serie_season.py
xtreamcodeserver/entry/vod.py
xtreamcodeserver/epg/epgchannel.py
xtreamcodeserver/epg/epgprogram.py
xtreamcodeserver/interfaces/credentialsprovider.py
xtreamcodeserver/interfaces/datetimeprovider.py
xtreamcodeserver/interfaces/entryprovider.py
xtreamcodeserver/interfaces/epgprovider.py
xtreamcodeserver/interfaces/stream.py
xtreamcodeserver/providers/inmemory/credentials_provider.py
xtreamcodeserver/providers/inmemory/entry_provider.py
xtreamcodeserver/providers/inmemory/epg_provider.py
xtreamcodeserver/stream/filesystemstream.py
xtreamcodeserver/stream/httpredirectstream.py
xtreamcodeserver/stream/httpstream.py
xtreamcodeserver/stream/memorystream.py
xtreamcodeserver/stream/playlistproxystream.py
xtreamcodeserver/stream/transcodestream.py
xtreamcodeserver/tests/test_credentials.py
xtreamcodeserver/tests/test_entry.py
xtreamcodeserver/tests/test_epg.py
xtreamcodeserver/tests/test_infos.py
xtreamcodeserver/tests/test_stream.py
xtreamcodeserver/utils/http_utils.py
xtreamcodeserver-1.1.0.dist-info/LICENSE
xtreamcodeserver-1.1.0.dist-info/METADATA
xtreamcodeserver-1.1.0.dist-info/WHEEL
xtreamcodeserver-1.1.0.dist-info/entry_points.txt
xtreamcodeserver-1.1.0.dist-info/top_level.txt
xtreamcodeserver-1.1.0.dist-info/RECORD
